{
   "bindings" : {
      "/actions/legacy" : {
	  "haptics" : [
         ],
         "poses" : [
         ],
         "sources" : [
			{
               "inputs" : {
                  "position" : {
                     "output" : "/actions/legacy/in/left_axis0_value"
                  }
               },
               "mode" : "trackpad",
               "path" : "/user/treadmill/input/trackpad"
            },
			{
               "inputs" : {
                  "position" : {
                     "output" : "/actions/legacy/in/left_axis0_value"
                  }
               },
               "mode" : "joystick",
               "path" : "/user/treadmill/input/joystick"
            }
         ]
      }
   },
   "category" : "legacy",
   "controller_type" : "example_controller",
   "description" : "Legacy mapping for example",
   "name" : "Legacy_Binding_Example",
   "options" : {
      "mirror_actions" : false,
      "returnBindingsWithLeftHand" : true,
      "simulated_controller_type" : "none"
    }
}
